gitlab_personal_issue_board/__init__.py
gitlab_personal_issue_board/caching.py
gitlab_personal_issue_board/controller.py
gitlab_personal_issue_board/gitlab.py
gitlab_personal_issue_board/model_validators.py
gitlab_personal_issue_board/models.py
gitlab_personal_issue_board/py.typed
gitlab_personal_issue_board/settings.py
gitlab_personal_issue_board/view_model.py
gitlab_personal_issue_board/data/__init__.py
gitlab_personal_issue_board/data/boards.py
gitlab_personal_issue_board/ui/Sortable.min.js
gitlab_personal_issue_board/ui/__init__.py
gitlab_personal_issue_board/ui/main.py
gitlab_personal_issue_board/ui/sortable.py
gitlab_personal_issue_board/ui/sortable_column.js
gitlab_personal_issue_board-0.0.3.dist-info/METADATA
gitlab_personal_issue_board-0.0.3.dist-info/WHEEL
gitlab_personal_issue_board-0.0.3.dist-info/entry_points.txt
gitlab_personal_issue_board-0.0.3.dist-info/licenses/LICENSE.txt
gitlab_personal_issue_board-0.0.3.dist-info/RECORD
