Metadata-Version: 2.4
Name: gitlab-personal-issue-board
Version: 0.0.3
Summary: Manage gitlab issues assigned to yourself locally for all groups and projects
Project-URL: Documentation, https://github.com/CarliJoy/gitlab_personal_issue_board/#readme
Project-URL: Issues, https://github.com/CarliJoy/gitlab_personal_issue_board/issues
Project-URL: Source, https://github.com/CarliJoy/gitlab_personal_issue_board/
Author-email: Carli Freudenberg <carli.freudenberg@energymeteo.de>
License-Expression: MIT
License-File: LICENSE.txt
Classifier: Development Status :: 4 - Beta
Classifier: Programming Language :: Python
Classifier: Programming Language :: Python :: 3.12
Classifier: Programming Language :: Python :: Implementation :: CPython
Classifier: Programming Language :: Python :: Implementation :: PyPy
Requires-Python: >=3.12
Requires-Dist: attrs>=25.3.0
Requires-Dist: click>=8.2.1
Requires-Dist: nicegui>=2.19.0
Requires-Dist: orjson>=3.10.18
Requires-Dist: platformdirs>=4.3.8
Requires-Dist: pydantic>=2.11.5
Requires-Dist: python-gitlab>=5.6.0
Requires-Dist: typed-settings>=24.6.0
